Pacote_Calculadora/__init__.py
Pacote_Calculadora/operacoes.py
Pacote_Calculadora-0.0.1.dist-info/METADATA
Pacote_Calculadora-0.0.1.dist-info/WHEEL
Pacote_Calculadora-0.0.1.dist-info/top_level.txt
Pacote_Calculadora-0.0.1.dist-info/RECORD
