Metadata-Version: 2.1
Name: Pacote-Calculadora
Version: 0.0.1
Summary: Calculadora basica para demonstração de criação de pacote
Home-page: https://github.com/MateusCDev/Criacao_Pacotes_Python
Author: Mateus Cesar de Araujo
Author-email: mateus.cesararaujo@hotmail.com
License: UNKNOWN
Platform: UNKNOWN
Requires-Python: >=3.8
